MANIFEST.in
README.md
setup.py
pytpu/__init__.py
pytpu/_bindings.py
pytpu/_converter_to_raw.py
pytpu.egg-info/PKG-INFO
pytpu.egg-info/SOURCES.txt
pytpu.egg-info/dependency_links.txt
pytpu.egg-info/entry_points.txt
pytpu.egg-info/not-zip-safe
pytpu.egg-info/requires.txt
pytpu.egg-info/top_level.txt
pytpu_tests/__init__.py
pytpu_tests/unit/__init__.py
pytpu_tests/unit/_helpres.py
pytpu_tests/unit/_lenet5.py
pytpu_tests/unit/_resnet50.py
pytpu_tests/unit/test_inference_error.py
pytpu_tests/unit/test_lenet5.py
pytpu_tests/unit/test_parallel.py
pytpu_tests/unit/test_program_lut_parameters.py
pytpu_tests/unit/test_resnet50.py
pytpu_tests/unit/test_total_mem.py
pytpu_tests/unit/test_tpu_exists.py
pytpu_tests/unit/test_watchdog_error.py
pytpu_tests/unit/test_ziptests.py