Metadata-Version: 2.1
Name: pytpu
Version: 15.0.20
Summary: TPU Python API
Home-page: http://git.mmp.iva-tech.ru/tpu_sw/iva_tpu_sdk
Author: IVA-Tech
Author-email: info@iva-tech.ru
License: UNKNOWN
Platform: UNKNOWN
Requires-Python: >=3.6
Provides-Extra: test
